sad_cin/__init__.py
sad_cin/main.py
sad_cin-0.5.1.dist-info/LICENSE
sad_cin-0.5.1.dist-info/METADATA
sad_cin-0.5.1.dist-info/WHEEL
sad_cin-0.5.1.dist-info/RECORD
