Metadata-Version: 2.3
Name: sad_cin
Version: 0.5.1
Summary: Sistemas de Apoio à Decisão multi critério, desenvolvida no Centro de Informática da Universidade Federal de Pernambuco
License: MIT
Author: Adiel Filho
Requires-Python: >=3.10
Classifier: License :: OSI Approved :: MIT License
Classifier: Programming Language :: Python :: 3
Classifier: Programming Language :: Python :: 3.10
Classifier: Programming Language :: Python :: 3.11
Classifier: Programming Language :: Python :: 3.12
Classifier: Programming Language :: Python :: 3.13
Requires-Dist: ftopsis-class-cin (==0.1.1)
Requires-Dist: rim-cin (==0.1.0)
Requires-Dist: topsis-cin (==0.1.1)
Requires-Dist: vikor-cin (==0.1.0)
Requires-Dist: wfrim-cin (==0.1.0)
